auto_round_kernel/__init__.py
auto_round_kernel/auto_round_kernel.cpython-314-x86_64-linux-gnu.so
auto_round_kernel.libs/libc10-13313050.so
auto_round_kernel.libs/libc10_xpu-aaa88a9c.so
auto_round_kernel.libs/libimf-1c15e626.so
auto_round_kernel.libs/libintlc-55c32384.so.5
auto_round_kernel.libs/libiomp5-31023e22.so
auto_round_kernel-0.9.0.dist-info/METADATA
auto_round_kernel-0.9.0.dist-info/WHEEL
auto_round_kernel-0.9.0.dist-info/top_level.txt
auto_round_kernel-0.9.0.dist-info/RECORD
