Metadata-Version: 2.4
Name: auto-round-kernel
Version: 0.9.0
Summary: Auto Round Kernel binary package
Home-page: https://github.com/intel/auto-round
Author-email: yu.luo@intel.com
License: Apache 2.0
Keywords: quantization,auto-around,LLM,kernel
Classifier: Intended Audience :: Science/Research
Classifier: Programming Language :: Python :: 3
Classifier: Topic :: Scientific/Engineering :: Artificial Intelligence
Classifier: License :: OSI Approved :: Apache Software License
Requires-Dist: torch==2.9.0+xpu
Requires-Dist: torchvision==0.24.0+xpu
Requires-Dist: torchaudio==2.9.0+xpu
Requires-Dist: dpcpp-cpp-rt==2025.2.1
Requires-Dist: onednn==2025.2.0
Dynamic: author-email
Dynamic: classifier
Dynamic: description
Dynamic: description-content-type
Dynamic: home-page
Dynamic: keywords
Dynamic: license
Dynamic: requires-dist
Dynamic: summary
